transparent_background/InSPyReNet.py
transparent_background/Remover.py
transparent_background/__init__.py
transparent_background/utils.py
transparent_background/backbones/SwinTransformer.py
transparent_background/modules/attention_module.py
transparent_background/modules/context_module.py
transparent_background/modules/decoder_module.py
transparent_background/modules/layers.py
transparent_background_dev-1.1.5.dev1.dist-info/LICENSE
transparent_background_dev-1.1.5.dev1.dist-info/METADATA
transparent_background_dev-1.1.5.dev1.dist-info/WHEEL
transparent_background_dev-1.1.5.dev1.dist-info/entry_points.txt
transparent_background_dev-1.1.5.dev1.dist-info/top_level.txt
transparent_background_dev-1.1.5.dev1.dist-info/RECORD
