Metadata-Version: 2.1
Name: transparent-background-dev
Version: 1.1.5.dev1
Summary: Make images with transparent background
Home-page: https://github.com/plemeri/transparent-background
Author: Taehun Kim
Author-email: taehoon1018@postech.ac.kr
Classifier: Programming Language :: Python :: 3
Classifier: License :: OSI Approved :: MIT License
Classifier: Operating System :: OS Independent
Requires-Python: >=3.8
License-File: LICENSE
Requires-Dist: torch (>=1.7.1)
Requires-Dist: torchvision (>=0.8.2)
Requires-Dist: opencv-python (>=4.6.0.66)
Requires-Dist: timm (>=0.6.11)
Requires-Dist: tqdm (>=4.64.1)
Requires-Dist: kornia (>=0.5.4)
Requires-Dist: gdown (>=4.5.4)
Requires-Dist: pyvirtualcam (>=0.6.0)
Requires-Dist: onnxruntime (>=1.13.1)
